zoho_crm/__init__.py
zoho_crm/api_client.py
zoho_crm-0.0.4.dist-info/METADATA
zoho_crm-0.0.4.dist-info/WHEEL
zoho_crm-0.0.4.dist-info/licenses/LICENCE
zoho_crm-0.0.4.dist-info/RECORD
